odoo8_addon_base_zugferd-8.0.1.0.0.99.dev5-nspkg.pth
odoo_addons/base_zugferd/README.rst
odoo_addons/base_zugferd/__init__.py
odoo_addons/base_zugferd/__openerp__.py
odoo_addons/base_zugferd/data/zugferd_codes.xml
odoo_addons/base_zugferd/i18n/base_zugferd.pot
odoo_addons/base_zugferd/static/description/icon.png
odoo8_addon_base_zugferd-8.0.1.0.0.99.dev5.dist-info/METADATA
odoo8_addon_base_zugferd-8.0.1.0.0.99.dev5.dist-info/WHEEL
odoo8_addon_base_zugferd-8.0.1.0.0.99.dev5.dist-info/namespace_packages.txt
odoo8_addon_base_zugferd-8.0.1.0.0.99.dev5.dist-info/top_level.txt
odoo8_addon_base_zugferd-8.0.1.0.0.99.dev5.dist-info/RECORD
