Metadata-Version: 2.1
Name: odoo8-addon-base-zugferd
Version: 8.0.1.0.0.99.dev5
Summary: Base module for ZUGFeRD
Home-page: http://www.akretion.com
Author: Akretion,Odoo Community Association (OCA)
Author-email: support@odoo-community.org
License: AGPL-3
Platform: UNKNOWN
Classifier: Programming Language :: Python
Classifier: Framework :: Odoo
Classifier: License :: OSI Approved :: GNU Affero General Public License v3
Requires-Python: ~=2.7
Requires-Dist: odoo8-addon-account-payment-unece
Requires-Dist: odoo8-addon-account-tax-unece
Requires-Dist: odoo8-addon-product-uom-unece
Requires-Dist: odoo (<9.0a,>=8.0a)
